recursive_diff/__init__.py
recursive_diff/cast.py
recursive_diff/dask_or_stub.py
recursive_diff/ncdiff.py
recursive_diff/proper_unstack.py
recursive_diff/py.typed
recursive_diff/recursive_diff.py
recursive_diff/recursive_eq.py
recursive_diff/tests/__init__.py
recursive_diff/tests/test_ncdiff.py
recursive_diff/tests/test_proper_unstack.py
recursive_diff/tests/test_recursive_diff.py
recursive_diff/tests/test_recursive_eq.py
recursive_diff-1.3.0.dist-info/METADATA
recursive_diff-1.3.0.dist-info/WHEEL
recursive_diff-1.3.0.dist-info/entry_points.txt
recursive_diff-1.3.0.dist-info/licenses/LICENSE
recursive_diff-1.3.0.dist-info/RECORD
